[
	{
		"group": "admin",
		"permissions": [
			{
				"resource": "*",
				"methods": "*",
				"action": "allow"
			}
		]
	},
	{
		"group": "user",
		"permissions": [
			{
				"resource": "user/userSecret",
				"methods": "*",
				"action": "allow"
      },
      {
				"resource": "user/guestSecret",
				"methods": "*",
				"action": "allow"
      }
		]
	},
	{
		"group": "guest",
		"permissions": [
      {
				"resource": "user/guestSecret",
				"methods": "*",
				"action": "allow"
			}
		]
	}
]
